gamecrafterclient/__init__.py
gamecrafterclient/client.py
gamecrafterclient/gameCrafterSession.py
gamecrafterclient/httpClient.py
gamecrafterclient/operations.py
gamecrafterclient-1.0.10.dist-info/LICENSE
gamecrafterclient-1.0.10.dist-info/LICENSE.txt
gamecrafterclient-1.0.10.dist-info/METADATA
gamecrafterclient-1.0.10.dist-info/WHEEL
gamecrafterclient-1.0.10.dist-info/top_level.txt
gamecrafterclient-1.0.10.dist-info/RECORD
