Metadata-Version: 2.1
Name: gamecrafterclient
Version: 1.0.10
Summary: Python API client for the game crafter.
Home-page: https://github.com/TheNextGuy32/gameCrafterClient
Author: Oliver Barnum
Author-email: oliverbarnum32@gmail.com
License: UNKNOWN
Download-URL: https://github.com/TheNextGuy32/gameCrafterClient/archive/1.0.4.tar.gz
Platform: UNKNOWN
Classifier: Programming Language :: Python :: 3.7
Classifier: License :: OSI Approved :: GNU General Public License v3 (GPLv3)
Classifier: Operating System :: OS Independent
Requires-Python: >=3.7
Requires-Dist: tabulate
Requires-Dist: asyncio
Requires-Dist: aiofile
Requires-Dist: aiohttp
